{
  "algorithm": "RandomForestClassifier",
  "n_estimators": 200,
  "max_depth": 6,
  "train_size": 45798,
  "test_size": 15267,
  "accuracy": 0.7658348071002816,
  "confusion_matrix": [
    [
      5893,
      3107
    ],
    [
      468,
      5799
    ]
  ],
  "timestamp": "2025-12-05T07:14:11.987539+00:00",
  "features": [
    "path_length",
    "payload_length",
    "has_admin_in_payload",
    "has_select_in_payload",
    "num_special_chars",
    "num_digits",
    "path_depth",
    "has_sql_keywords",
    "has_xss_pattern",
    "payload_entropy"
  ],
  "feature_names": [
    "path_length",
    "payload_length",
    "has_admin_in_payload",
    "has_select_in_payload",
    "num_special_chars",
    "num_digits",
    "path_depth",
    "has_sql_keywords",
    "has_xss_pattern",
    "payload_entropy"
  ],
  "data_source": "CSIC",
  "positive_label": 1,
  "label_meaning": {
    "0": "benign",
    "1": "malicious"
  },
  "random_seed": 42,
  "decision_threshold": 0.47
}